hls4ml/__init__.py
hls4ml/_version.py
hls4ml/backends/__init__.py
hls4ml/backends/backend.py
hls4ml/backends/template.py
hls4ml/backends/catapult/__init__.py
hls4ml/backends/catapult/catapult_backend.py
hls4ml/backends/catapult/catapult_types.py
hls4ml/backends/catapult/passes/__init__.py
hls4ml/backends/catapult/passes/bn_quant.py
hls4ml/backends/catapult/passes/broadcast_stream.py
hls4ml/backends/catapult/passes/conv_same_pad.py
hls4ml/backends/catapult/passes/conv_stream.py
hls4ml/backends/catapult/passes/convolution_templates.py
hls4ml/backends/catapult/passes/convolution_winograd.py
hls4ml/backends/catapult/passes/core_templates.py
hls4ml/backends/catapult/passes/fifo_depth_optimization.py
hls4ml/backends/catapult/passes/garnet_templates.py
hls4ml/backends/catapult/passes/im2col_codegen.py
hls4ml/backends/catapult/passes/merge_templates.py
hls4ml/backends/catapult/passes/pointwise.py
hls4ml/backends/catapult/passes/pooling_templates.py
hls4ml/backends/catapult/passes/quantization_templates.py
hls4ml/backends/catapult/passes/recurrent_templates.py
hls4ml/backends/catapult/passes/reshaping_templates.py
hls4ml/backends/catapult/passes/resource_strategy.py
hls4ml/backends/catapult/passes/transform_types.py
hls4ml/backends/fpga/__init__.py
hls4ml/backends/fpga/fpga_backend.py
hls4ml/backends/fpga/fpga_layers.py
hls4ml/backends/fpga/fpga_types.py
hls4ml/backends/fpga/passes/__init__.py
hls4ml/backends/fpga/passes/bram_weights.py
hls4ml/backends/fpga/passes/clone.py
hls4ml/backends/fpga/passes/embedding.py
hls4ml/backends/fpga/passes/final_reshape.py
hls4ml/backends/fpga/passes/fix_softmax_table_size.py
hls4ml/backends/fpga/passes/hgq_proxy_model.py
hls4ml/backends/fpga/passes/inplace_parallel_reshape.py
hls4ml/backends/fpga/passes/inplace_stream_flatten.py
hls4ml/backends/fpga/passes/remove_softmax.py
hls4ml/backends/fpga/passes/repack_stream.py
hls4ml/backends/fpga/passes/xnor_pooling.py
hls4ml/backends/oneapi/__init__.py
hls4ml/backends/oneapi/oneapi_backend.py
hls4ml-1.2.0.dist-info/licenses/LICENSE
hls4ml-1.2.0.dist-info/METADATA
hls4ml-1.2.0.dist-info/WHEEL
hls4ml-1.2.0.dist-info/entry_points.txt
hls4ml-1.2.0.dist-info/top_level.txt
hls4ml-1.2.0.dist-info/RECORD
