Metadata-Version: 2.4
Name: hls4ml
Version: 1.2.0
Summary: Machine learning in FPGAs using HLS
Author: hls4ml Team
License: Apache-2.0
Project-URL: Homepage, https://fastmachinelearning.org/hls4ml
Classifier: Development Status :: 4 - Beta
Classifier: Intended Audience :: Developers
Classifier: Intended Audience :: Science/Research
Classifier: License :: OSI Approved :: Apache Software License
Classifier: Programming Language :: C++
Classifier: Programming Language :: Python :: 3 :: Only
Classifier: Programming Language :: Python :: 3.10
Classifier: Programming Language :: Python :: 3.11
Classifier: Programming Language :: Python :: 3.12
Classifier: Programming Language :: Python :: 3.13
Classifier: Programming Language :: Python :: 3.14
Classifier: Topic :: Software Development :: Libraries
Classifier: Topic :: Software Development :: Libraries :: Python Modules
Requires-Python: >=3.10
License-File: LICENSE
Requires-Dist: h5py
Requires-Dist: numpy
Requires-Dist: pydigitalwavetools==1.1
Requires-Dist: pyyaml
Requires-Dist: quantizers
Provides-Extra: da
Requires-Dist: da4ml<0.5,>=0.4; extra == "da"
Provides-Extra: doc
Requires-Dist: sphinx; extra == "doc"
Requires-Dist: sphinx-contributors; extra == "doc"
Requires-Dist: sphinx-github-changelog; extra == "doc"
Requires-Dist: sphinx-rtd-theme; extra == "doc"
Requires-Dist: sphinx-tabs; extra == "doc"
Provides-Extra: hgq
Requires-Dist: hgq>=0.2.3; extra == "hgq"
Provides-Extra: hgq2
Requires-Dist: hgq2>=0.0.1; extra == "hgq2"
Provides-Extra: keras-v3
Requires-Dist: keras>=3.10; extra == "keras-v3"
Provides-Extra: onnx
Requires-Dist: onnx>=1.4; extra == "onnx"
Provides-Extra: optimization
Requires-Dist: keras-tuner==1.1.3; extra == "optimization"
Requires-Dist: ortools==9.4.1874; extra == "optimization"
Requires-Dist: packaging; extra == "optimization"
Provides-Extra: profiling
Requires-Dist: matplotlib; extra == "profiling"
Requires-Dist: pandas; extra == "profiling"
Requires-Dist: seaborn; extra == "profiling"
Provides-Extra: qkeras
Requires-Dist: qkeras; extra == "qkeras"
Requires-Dist: tensorflow<=2.14.1,>=2.8; extra == "qkeras"
Requires-Dist: tensorflow-model-optimization<=0.7.5; extra == "qkeras"
Provides-Extra: quartus-report
Requires-Dist: calmjs-parse; extra == "quartus-report"
Requires-Dist: tabulate; extra == "quartus-report"
Provides-Extra: sr
Requires-Dist: sympy>=1.13.1; extra == "sr"
Provides-Extra: testing
Requires-Dist: calmjs-parse; extra == "testing"
Requires-Dist: hgq>=0.2.3; extra == "testing"
Requires-Dist: onnx>=1.4; extra == "testing"
Requires-Dist: pytest; extra == "testing"
Requires-Dist: pytest-cov; extra == "testing"
Requires-Dist: pytest-randomly; extra == "testing"
Requires-Dist: qonnx; extra == "testing"
Requires-Dist: tabulate; extra == "testing"
Requires-Dist: torch; extra == "testing"
Dynamic: license-file
